{
  "timestamp": "2025-08-26T14:46:05.115661",
  "uptime": 66999.43896102905,
  "services": {
    "backend": {
      "service": "backend",
      "status": "healthy",
      "response_time": 0.006537914276123047,
      "timestamp": "2025-08-26 14:43:42.520572",
      "message": "Service responding normally",
      "details": {
        "error_count": 0,
        "processing": true,
        "status": "healthy",
        "total_events": 624453,
        "uptime": 66869.84512996674
      }
    },
    "frontend": {
      "service": "frontend",
      "status": "critical",
      "response_time": 0.12688589096069336,
      "timestamp": "2025-08-26 14:43:42.647509",
      "message": "HTTP 404: Not Found",
      "details": {}
    }
  },
  "system_metrics": null,
  "availability_24h": {
    "backend": 100.0,
    "frontend": 0.0
  },
  "recent_alerts": [
    {
      "level": "critical",
      "metric": "service_health",
      "service": "frontend",
      "value": "critical",
      "threshold": "healthy",
      "message": "Service frontend is critical: HTTP 404: Not Found",
      "timestamp": "2025-08-26T13:50:21.069450"
    },
    {
      "level": "critical",
      "metric": "service_health",
      "service": "frontend",
      "value": "critical",
      "threshold": "healthy",
      "message": "Service frontend is critical: HTTP 404: Not Found",
      "timestamp": "2025-08-26T13:55:23.514123"
    },
    {
      "level": "critical",
      "metric": "service_health",
      "service": "frontend",
      "value": "critical",
      "threshold": "healthy",
      "message": "Service frontend is critical: HTTP 404: Not Found",
      "timestamp": "2025-08-26T14:00:25.748139"
    },
    {
      "level": "critical",
      "metric": "service_health",
      "service": "frontend",
      "value": "critical",
      "threshold": "healthy",
      "message": "Service frontend is critical: HTTP 404: Not Found",
      "timestamp": "2025-08-26T14:05:27.800161"
    },
    {
      "level": "critical",
      "metric": "service_health",
      "service": "frontend",
      "value": "critical",
      "threshold": "healthy",
      "message": "Service frontend is critical: HTTP 404: Not Found",
      "timestamp": "2025-08-26T14:10:29.678225"
    },
    {
      "level": "critical",
      "metric": "service_health",
      "service": "frontend",
      "value": "critical",
      "threshold": "healthy",
      "message": "Service frontend is critical: HTTP 404: Not Found",
      "timestamp": "2025-08-26T14:15:31.528652"
    },
    {
      "level": "critical",
      "metric": "service_health",
      "service": "frontend",
      "value": "critical",
      "threshold": "healthy",
      "message": "Service frontend is critical: HTTP 404: Not Found",
      "timestamp": "2025-08-26T14:20:33.528059"
    },
    {
      "level": "critical",
      "metric": "service_health",
      "service": "frontend",
      "value": "critical",
      "threshold": "healthy",
      "message": "Service frontend is critical: HTTP 404: Not Found",
      "timestamp": "2025-08-26T14:25:35.354982"
    },
    {
      "level": "critical",
      "metric": "service_health",
      "service": "frontend",
      "value": "critical",
      "threshold": "healthy",
      "message": "Service frontend is critical: HTTP 404: Not Found",
      "timestamp": "2025-08-26T14:30:37.278085"
    },
    {
      "level": "critical",
      "metric": "service_health",
      "service": "frontend",
      "value": "critical",
      "threshold": "healthy",
      "message": "Service frontend is critical: HTTP 404: Not Found",
      "timestamp": "2025-08-26T14:35:39.232724"
    },
    {
      "level": "critical",
      "metric": "service_health",
      "service": "frontend",
      "value": "critical",
      "threshold": "healthy",
      "message": "Service frontend is critical: HTTP 404: Not Found",
      "timestamp": "2025-08-26T14:40:41.504162"
    },
    {
      "level": "critical",
      "metric": "service_health",
      "service": "frontend",
      "value": "critical",
      "threshold": "healthy",
      "message": "Service frontend is critical: HTTP 404: Not Found",
      "timestamp": "2025-08-26T14:45:43.572197"
    }
  ],
  "alert_summary": {
    "critical": 12,
    "warning": 0
  }
}